custom_latex/__init__.py
custom_latex/custom_latex.py
custom_latex-0.1.0.dist-info/METADATA
custom_latex-0.1.0.dist-info/WHEEL
custom_latex-0.1.0.dist-info/RECORD
