Metadata-Version: 2.1
Name: custom-latex
Version: 0.1.0
Summary: Study repository, liblrary generating .tex files with tables and images.
Author: e.davletshin
Author-email: e.davletshin@gmail.com
Requires-Python: >=3.10,<4.0
Classifier: Programming Language :: Python :: 3
Classifier: Programming Language :: Python :: 3.10
Classifier: Programming Language :: Python :: 3.11
Classifier: Programming Language :: Python :: 3.12
